tribology/__init__.py
tribology/boundary_element.py
tribology/constants.py
tribology/data_import.py
tribology/dowson_hamrock.py
tribology/hertz.py
tribology/lubrication.py
tribology/process_slim_mapper.py
tribology/roller_bearings.py
tribology/rough_surfaces.py
tribology/tribology.py
tribology/p3can/BluPrintAxialThrustBear.py
tribology/p3can/BluPrintBallOnDisk.py
tribology/p3can/BluPrintBallOnThreePlates.py
tribology/p3can/BluPrintCylRollBear.py
tribology/p3can/BluPrintFourBall.py
tribology/p3can/BluPrintPinOnDisk.py
tribology/p3can/BluPrintRingOnRing.py
tribology/p3can/BluPrintRollBear.py
tribology/p3can/BluPrintSim.py
tribology/p3can/BluPrintTriboSys.py
tribology/p3can/Constants.py
tribology/p3can/ContactBodies.py
tribology/p3can/USER_INPUT.py
tribology/p3can/__init__.py
tribology/p3can/artificial_surf.py
tribology/p3can/cartesian_plot_functions.py
tribology/p3can/check_environment.py
tribology/p3can/generate_latex_output.py
tribology/p3can/generate_profile.py
tribology/p3can/hertz_equations.py
tribology/p3can/import_user_input.py
tribology/p3can/influ_matrix_management.py
tribology/p3can/load_distr_cyl_rol_bear.py
tribology/p3can/numeric_methods.py
tribology/p3can/p3can.py
tribology/p3can/polar_plot_functions.py
tribology/p3can/pub_funs_CylRolBear.py
tribology/p3can/setup_tribosystem.py
tribology/p3can/solve_half_space.py
tribology/p3can/system_functions.py
tribology/p3can/BearingProfiles/81212-RE-1.txt
tribology/p3can/BearingProfiles/NU206-IR-1.txt
tribology/p3can/BearingProfiles/NU206-IR-2.txt
tribology/p3can/BearingProfiles/NU206-RE-1.txt
tribology/p3can/BearingProfiles/NU206-RE-2.txt
tribology/p3can/BearingProfiles/NU208-IR-1.txt
tribology/p3can/BearingProfiles/NU2208-IR-1.txt
tribology/p3can/LatexTemplates/p3can-calculation-report-template.tex
tribology/p3can/LatexTemplates/template-axial-thrust-bearing.tex
tribology/p3can/LatexTemplates/template-ball-on-disk.tex
tribology/p3can/LatexTemplates/template-ball-on-three-plates.tex
tribology-0.5.16.dist-info/LICENSE.txt
tribology-0.5.16.dist-info/METADATA
tribology-0.5.16.dist-info/WHEEL
tribology-0.5.16.dist-info/top_level.txt
tribology-0.5.16.dist-info/RECORD
