Metadata-Version: 2.1
Name: tribology
Version: 0.5.16
Summary: functions and constants for tribology research
Home-page: https://github.com/moritzploss/tribology
Author: Moritz Ploss
Author-email: moritz.ploss@gmail.com
License: MIT
Keywords: tribology machine design research
Platform: UNKNOWN
Classifier: Development Status :: 4 - Beta
Classifier: Intended Audience :: Science/Research
Classifier: Topic :: Scientific/Engineering
Classifier: License :: OSI Approved :: MIT License
Classifier: Programming Language :: Python :: 3.5
Classifier: Programming Language :: Python :: 3.6
Requires-Python: >=3.5
Requires-Dist: numpy (<=1.16.1)
Requires-Dist: numexpr
Requires-Dist: scipy
Requires-Dist: opencv-python (==3.4.2.16)
Requires-Dist: matplotlib
